<?xml version="1.0" encoding="utf-8"?>
<databaseChangeLog
        xmlns="http://www.liquibase.org/xml/ns/dbchangelog"
        xmlns:xsi="http://www.w3.org/2001/XMLSchema-instance"
        xsi:schemaLocation="http://www.liquibase.org/xml/ns/dbchangelog
                        http://www.liquibase.org/xml/ns/dbchangelog/dbchangelog-3.4.xsd">

    <changeSet id="create_table_endereco" author="carmelito.benali">
        <validCheckSum>ANY</validCheckSum>
        <preConditions onFail="MARK_RAN" onFailMessage="A tabela endereco já existe"/>
        <createTable tableName="endereco" schemaName="elo">
            <column type="BIGINT" name="id"><constraints nullable="false"/></column>
            <column type="BIGINT" name="pessoa_id"><constraints nullable="false"/></column>
            <column type="varchar(10)" name="cep"><constraints nullable="false"/></column>
            <column type="varchar(150)" name="logradouro"><constraints nullable="false"/></column>
            <column type="varchar(10)" name="numero"><constraints nullable="false"/></column>
            <column type="varchar(100)" name="cidade"><constraints nullable="false"/></column>
            <column type="varchar(2)" name="uf"><constraints nullable="false"/></column>
            <column type="varchar(100)" name="bairro"><constraints nullable="false"/></column>
        </createTable>
        <addPrimaryKey schemaName="elo" tableName="endereco" columnNames="id" constraintName="endereco_pk"/>
        <addForeignKeyConstraint baseTableSchemaName="elo"
                                baseTableName="endereco"
                                baseColumnNames="pessoa_id"
                                constraintName="fk_pessoa"
                                referencedTableSchemaName="elo"
                                referencedTableName="pessoa"
                                referencedColumnNames="id"/>
    </changeSet>

</databaseChangeLog>
